zema_emc_annotated/__init__.py
zema_emc_annotated/data_types.py
zema_emc_annotated/dataset.py
zema_emc_annotated/examples/read_dataset.ipynb
zema_emc_annotated-0.7.1.dist-info/WHEEL
zema_emc_annotated-0.7.1.dist-info/METADATA
zema_emc_annotated-0.7.1.dist-info/LICENSE
zema_emc_annotated-0.7.1.dist-info/RECORD
