Metadata-Version: 2.1
Name: zema-emc-annotated
Version: 0.7.1
Summary: API to the annotated ZeMA dataset about an electro-mechanical cylinder
License: MIT
Keywords: FAIR data,measurement uncertainty
Author: Bjoern Ludwig
Author-email: bjoern.ludwig@ptb.de
Requires-Python: >=3.10,<4.0
Classifier: Development Status :: 2 - Pre-Alpha
Classifier: Intended Audience :: Science/Research
Classifier: License :: OSI Approved :: MIT License
Classifier: Programming Language :: Python :: 3
Classifier: Programming Language :: Python :: 3.10
Classifier: Programming Language :: Python :: 3.11
Classifier: Topic :: Scientific/Engineering :: Mathematics
Provides-Extra: docs
Requires-Dist: h5py (>=3.7.0,<4.0.0)
Requires-Dist: ipython (>=8.8.0,<9.0.0) ; extra == "docs"
Requires-Dist: myst-parser (>=0.18.1,<0.19.0) ; extra == "docs"
Requires-Dist: nbsphinx (>=0.8.12,<0.9.0) ; extra == "docs"
Requires-Dist: numpy (>=1.24.1,<2.0.0)
Requires-Dist: pooch (>=1.6.0,<2.0.0)
Requires-Dist: sphinx (>=5.3.0,<6.0.0) ; extra == "docs"
Requires-Dist: sphinx-rtd-theme (>=1.1.1,<2.0.0) ; extra == "docs"
Requires-Dist: tqdm (>=4.64.1,<5.0.0)
